redssh/__init__.py
redssh/enums.py
redssh/exceptions.py
redssh/redssh.py
redssh/utils.py
redssh/clients/__init__.py
redssh/clients/base_client.py
redssh/clients/base_sftp.py
redssh/clients/baseclient.py
redssh/clients/libssh/__init__.py
redssh/clients/libssh/enums.py
redssh/clients/libssh/libssh.py
redssh/clients/libssh/redsshlibssh.py
redssh/clients/libssh/scp.py
redssh/clients/libssh/sftp.py
redssh/clients/libssh/tunneling.py
redssh/clients/libssh/x11.py
redssh/clients/libssh2/__init__.py
redssh/clients/libssh2/enums.py
redssh/clients/libssh2/libssh2.py
redssh/clients/libssh2/redsshlibssh2.py
redssh/clients/libssh2/scp.py
redssh/clients/libssh2/sftp.py
redssh/clients/libssh2/tunneling.py
redssh/clients/libssh2/x11.py
redssh-3.0.1.dist-info/LICENSE
redssh-3.0.1.dist-info/METADATA
redssh-3.0.1.dist-info/WHEEL
redssh-3.0.1.dist-info/top_level.txt
redssh-3.0.1.dist-info/RECORD
