Metadata-Version: 2.1
Name: redssh
Version: 3.0.1
Summary: An SSH automation library.
Home-page: https://bitbucket.org/Red_M/RedSSH
Author: Red_M
Author-email: redssh_pypi@red-m.net
License: GPLv2
Platform: Posix
Classifier: Development Status :: 5 - Production/Stable
Classifier: Programming Language :: Python :: Implementation :: CPython
Classifier: Programming Language :: Python
Classifier: Programming Language :: Python :: 3
Classifier: Programming Language :: Python :: 3.4
Classifier: Programming Language :: Python :: 3.5
Classifier: Programming Language :: Python :: 3.6
Classifier: Programming Language :: Python :: 3.7
Classifier: Programming Language :: Python :: 3.8
Classifier: Programming Language :: Python :: 3.9
Classifier: Programming Language :: Python :: 3.10
Classifier: Intended Audience :: Developers
Classifier: Topic :: Software Development :: Libraries
Classifier: Topic :: Software Development :: Libraries :: Python Modules
Classifier: Topic :: System :: Shells
Classifier: Topic :: System :: Networking
Classifier: Operating System :: POSIX
Classifier: Operating System :: POSIX :: Linux
Classifier: Operating System :: POSIX :: BSD
Classifier: Operating System :: Microsoft :: Windows
Classifier: Operating System :: MacOS :: MacOS X
Classifier: Operating System :: OS Independent
License-File: LICENSE
Requires-Dist: redlibssh2 (>=2.1.1-1)
Requires-Dist: redlibssh (>=2.0.3)
Provides-Extra: docs
Requires-Dist: sphinx ; extra == 'docs'
Requires-Dist: redlibssh (>=2.0.3) ; extra == 'docs'
Requires-Dist: sphinx-rtd-theme ; extra == 'docs'
Requires-Dist: redlibssh2 (>=2.1.1-1) ; extra == 'docs'
Provides-Extra: tests
Requires-Dist: redlibssh (>=2.0.3) ; extra == 'tests'
Requires-Dist: coveralls ; extra == 'tests'
Requires-Dist: redlibssh2 (>=2.1.1-1) ; extra == 'tests'
Requires-Dist: pylint ; extra == 'tests'
Requires-Dist: pytest-cov ; extra == 'tests'
Requires-Dist: safety ; extra == 'tests'
Requires-Dist: bandit ; extra == 'tests'
Requires-Dist: requests[socks] ; extra == 'tests'
Requires-Dist: jinja2 ; extra == 'tests'
